<?xml version="1.0" encoding="utf-8"?>
<metadata>
	<layout title="OSM_MENU_GEOPOSITION">
		<message>
			<![CDATA[COM_JTG_GEOPOSITION_LAYOUT_ DESCRIPTION]]>
		</message>
	</layout>
	<state>
		<name>COM_JTG_MENU_GEOPOSITION</name>
		<description>COM_JTG_GEOPOSITION_LAYOUT_DESCRIPTION</description>
		<config><fields name="params"><fieldset name="basic" label="basic">
			<field type="spacer" default="OSM_MENU_DEFAULT_LAT_LON" />
			<field name="osm_geo_lat" type="text" default="45" size="10" label="COM_JTG_MENU_DEFAULT_LAT" description="COM_JTG_TT_MENU_DEFAULT_LAT" />
			<field name="osm_geo_lon" type="text" default="0" size="10" label="COM_JTG_MENU_DEFAULT_LON" description="COM_JTG_TT_MENU_DEFAULT_LON" />
			<field name="osm_geo_zoom" type="list" default="1" label="COM_JTG_MENU_DEFAULT_ZOOM" description="COM_JTG_TT_MENU_DEFAULT_ZOOM">
				<option value="0">COM_JTG_MENU_ZOOM_0</option>
				<option value="1">1</option>
				<option value="2">2</option>
				<option value="3">3</option>
				<option value="4">4</option>
				<option value="5">5</option>
				<option value="6">6</option>
				<option value="7">7</option>
				<option value="8">8</option>
				<option value="9">9</option>
				<option value="10">10</option>
				<option value="11">11</option>
				<option value="12">12</option>
				<option value="13">13</option>
				<option value="14">14</option>
				<option value="15">15</option>
				<option value="16">16</option>
				<option value="17">17</option>
				<option value="18">COM_JTG_MENU_ZOOM_18</option>
			</field>
			<field type="spacer" default="OSM_MENU_DEFAULT_LAT_LON_SAVED" />
			<field name="osm_geo_zoom_loggedin" type="list" default="14" label="COM_JTG_MENU_DEFAULT_ZOOM_SAVED" description="COM_JTG_TT_MENU_DEFAULT_ZOOM_SAVED">
				<option value="0">COM_JTG_MENU_ZOOM_0</option>
				<option value="1">1</option>
				<option value="2">2</option>
				<option value="3">3</option>
				<option value="4">4</option>
				<option value="5">5</option>
				<option value="6">6</option>
				<option value="7">7</option>
				<option value="8">8</option>
				<option value="9">9</option>
				<option value="10">10</option>
				<option value="11">11</option>
				<option value="12">12</option>
				<option value="13">13</option>
				<option value="14">14</option>
				<option value="15">15</option>
				<option value="16">16</option>
				<option value="17">17</option>
				<option value="18">COM_JTG_MENU_ZOOM_18</option>
			</field>
		</fieldset></fields></config>
<!--		<advanced>
		</advanced>-->
	</state>
</metadata>
